[
  {
    "id": "globalAlert",
    "name": "Global Alert Page",
    "configurationSchemaSets": []
  },
  {
    "id": "page",
    "name": "Page",
    "configurationSchemaSets": [
      {
        "name": "Settings",
        "configurations": [
          {
            "name": "seo",
            "schema": {
              "title": "SEO",
              "description": "Search Engine Optimization options",
              "type": "object",
              "widget": {
                "ui:ObjectFieldTemplate": "GoogleSeoPreview"
              },
              "required": ["slug", "title", "description"],
              "properties": {
                "slug": {
                  "title": "Path",
                  "type": "string",
                  "default": "/"
                },
                "title": {
                  "title": "Default page title",
                  "description": "Display this title when no other tile is available",
                  "type": "string",
                  "default": "FastStore"
                },
                "description": {
                  "title": "Meta tag description",
                  "type": "string",
                  "default": "A beautifuly designed store"
                },
                "canonical": {
                  "title": "Canonical url for the page",
                  "type": "string"
                }
              }
            }
          }
        ]
      }
    ]
  },
  {
    "id": "pdp",
    "name": "Product Page",
    "configurationSchemaSets": []
  }
]
